YTDownl/__init__.py
YTDownl-0.1.2.dist-info/METADATA
YTDownl-0.1.2.dist-info/WHEEL
YTDownl-0.1.2.dist-info/entry_points.txt
YTDownl-0.1.2.dist-info/top_level.txt
YTDownl-0.1.2.dist-info/RECORD
