Metadata-Version: 2.1
Name: YTDownl
Version: 0.1.2
Summary: A Open-Source & Free YouTube Downloader
Home-page: https://github.com/TechGeeks-Dev/YTDownl
Author: TechGeeks
Author-email: YTDownl@tgeeks.cf
License: UNKNOWN
Platform: UNKNOWN
Classifier: Programming Language :: Python :: 3
Classifier: License :: OSI Approved :: MIT License
Classifier: Operating System :: OS Independent
Requires-Python: >=3.6
Requires-Dist: pytube
